resume.py
resume-0.13.dist-info/DESCRIPTION.rst
resume-0.13.dist-info/METADATA
resume-0.13.dist-info/RECORD
resume-0.13.dist-info/WHEEL
resume-0.13.dist-info/entry_points.txt
resume-0.13.dist-info/metadata.json
resume-0.13.dist-info/top_level.txt
