Metadata-Version: 2.0
Name: resume
Version: 0.13
Summary: Save/Restore interpreter running state to resume interruped computations
Home-page: https://github.com/asteriogonzalez/resume
Author: Asterio Gonzalez
Author-email: asterio.gonzalez@gmail.com
License: MIT
Keywords: testing,pytest,long_run,resume
Platform: UNKNOWN
Classifier: Development Status :: 3 - Alpha
Classifier: Topic :: Software Development :: Testing
Classifier: Intended Audience :: Developers
Classifier: Operating System :: OS Independent
Requires-Dist: numpy
